pyevaljs3/__init__.py
pyevaljs3/__version__.py
pyevaljs3/_node_program.py
pyevaljs3/evaljs.py
pyevaljs3/exception.py
pyevaljs3/runner.py
pyevaljs3/runtime.py
pyevaljs3/setting.py
pyevaljs3/utils.py
pyevaljs3-0.2.0.dist-info/LICENSE
pyevaljs3-0.2.0.dist-info/METADATA
pyevaljs3-0.2.0.dist-info/WHEEL
pyevaljs3-0.2.0.dist-info/top_level.txt
pyevaljs3-0.2.0.dist-info/RECORD
